{"text": "Apple ID replaced with someone else's after iOS 6 upgrade (Security breach)\n\nI just updated my iPad retina (3rd generation) with iOS 6 and now my Apple ID\nhas been replaced with someone else's ID.\n\niTunes Settings\n\nAnd its not jailbroken either. How did someone manage to do that? This is a\nserious security breach, I think.\n\nI logged out of that Apple ID but how can I be sure that they are not tracking\nanything and won't be able to purchase through my account?\n\n", "ents": [{"start": 0, "end": 5, "label": "ORG"}, {"start": 48, "end": 49, "label": "CARDINAL"}, {"start": 108, "end": 111, "label": "ORDINAL"}, {"start": 133, "end": 134, "label": "CARDINAL"}, {"start": 146, "end": 151, "label": "ORG"}, {"start": 193, "end": 195, "label": "ORG"}, {"start": 347, "end": 352, "label": "ORG"}]}